chesstoc/__init__.py
chesstoc/__main__.py
chesstoc/eco/eco.json
chesstoc/templates/chesstoc.css
chesstoc/templates/template.html
python_chess_toc-0.1.1.dist-info/LICENSE
python_chess_toc-0.1.1.dist-info/METADATA
python_chess_toc-0.1.1.dist-info/WHEEL
python_chess_toc-0.1.1.dist-info/top_level.txt
python_chess_toc-0.1.1.dist-info/RECORD
