Metadata-Version: 2.1
Name: python-chess-toc
Version: 0.1.1
Summary: Create a graphical table of contents for chess games with engine analysis
Home-page: https://github.com/i-tub/python-chess-toc
Author: Ivan Tubert-Brohman
Author-email: ivan.tubert@gmail.com
License: GPL-3.0+
Keywords: chess pgn svg html
Platform: UNKNOWN
Classifier: Development Status :: 3 - Alpha
Classifier: License :: OSI Approved :: GNU General Public License v3 or later (GPLv3+)
Classifier: Operating System :: OS Independent
Classifier: Programming Language :: Python
Classifier: Programming Language :: Python :: 3
Classifier: Programming Language :: Python :: 3 :: Only
Classifier: Topic :: Games/Entertainment :: Board Games
Requires-Python: >=3.4
Requires-Dist: python-chess
Requires-Dist: svgutils
Requires-Dist: matplotlib
Requires-Dist: jinja2
